{"sEOxg/5w8LuDIL9cjKk4XA==":"19967_image-1-122x122.png","NLeIzKzDNpGsHtibCya8hA==":"1508926764.7278-98511-imagefile-1920x1080.jpg","jYk3gJyhFl0aIOccmOXG3w==":"usluga_truby300-300x300.jpg","XdYPaLasBKL2dW3Y3E5a4Q==":"usluga_dushevaya2-300-300x300.jpg","J4JMR2JATY9bZM5UzYIMCw==":"usluga_vanna300-300x300.jpg","JBeJZLTq5jY7a9YDarLVwQ==":"usluga_djakuzi300-300x300.jpg","pa5Dkwo/T1qgW/t0h+fQvA==":"background5.jpg","ai5pD6v8GIStT4V6Dtm4aw==":"usluga_unitaz2-300-300x300.jpg","YndlKx/JSjTB6QbStHepyg==":"usluga_rakovina2-300-300x300.jpg","YNZK9veZKAmy3FbxwAYpUg==":"usluga_zamenasmesitelya2-300-300x300.jpg","M5lo4FsoPGdW+L7pHpXUZA==":"usluga_tech300-300x300.jpg","M4L7wl6UxhTpqTdZbuwJrw==":"2825889881-400x300.jpg","jk4nzOYfZwG0mHteWDEmGg==":"2825889881-400x300.jpeg","npQa+M8+FiT26rtek7ZuPQ==":"2825889881-1-400x300.jpeg","XLhVtH6ADiNKcHUgcuPKoQ==":"2825889881-2-400x300.jpeg","LgcddNWeBRn3/zYUAuUlDQ==":"2825889881-3-400x300.jpeg","6g79iLhGLL3fV3Yq2b0TWA==":"2193027014-400x644.jpeg","UAc7kepzJPkrSn4uqTRvmw==":"background4.jpg"}